ebi_i2rf-0.0.4.dist-info/licenses/LICENSE.txt
i2rf/wsr2.py
i2rf/i2rf_data/WSR_RefData.dat
ebi_i2rf-0.0.4.dist-info/METADATA
ebi_i2rf-0.0.4.dist-info/WHEEL
ebi_i2rf-0.0.4.dist-info/top_level.txt
ebi_i2rf-0.0.4.dist-info/RECORD
