Metadata-Version: 2.4
Name: ebi_i2rf
Version: 0.0.4
Summary: Post processing package for the I2RF tutorial at EBI-TFS (Karlsruhe Institute of Technology)
Author-email: David Maerker <david.maerker@kit.edu>
License-Expression: MIT
Keywords: EBI-TFS,I2RF,i2rf,KIT-EBI
Classifier: Programming Language :: Python :: 3
Classifier: Operating System :: OS Independent
Requires-Python: >=3.8
License-File: LICENSE.txt
Requires-Dist: numpy
Requires-Dist: pandas
Requires-Dist: setuptools
Requires-Dist: wheel
Dynamic: license-file
